locCSN/DistP.py
locCSN/__init__.py
locCSN/csn.py
locCSN/utils.py
locCSN-0.0.12.dist-info/LICENSE
locCSN-0.0.12.dist-info/METADATA
locCSN-0.0.12.dist-info/WHEEL
locCSN-0.0.12.dist-info/top_level.txt
locCSN-0.0.12.dist-info/RECORD
