Metadata-Version: 2.1
Name: locCSN
Version: 0.0.12
Summary: locCSN is a python package for local cell specific networks.
Home-page: https://github.com/xuranw/locCSN
Author: Xuran Wang
Author-email: xuranw@andrew.cmu.edu
License: MIT
Platform: UNKNOWN
Classifier: Development Status :: 4 - Beta
Classifier: License :: OSI Approved :: MIT License
Classifier: Programming Language :: Python
Classifier: Programming Language :: Python :: 3.5
Classifier: Programming Language :: Python :: 3.6
Classifier: Topic :: Software Development :: Libraries
Classifier: Topic :: Software Development :: Libraries :: Python Modules
Classifier: Intended Audience :: Developers
Requires-Python: >=3.5
License-File: LICENSE
Requires-Dist: numpy
Requires-Dist: pandas
Requires-Dist: scipy
Requires-Dist: matplotlib
Requires-Dist: scanpy
Requires-Dist: joblib
